labs_cdk/__init__.py
labs_cdk/labs_cdk_stack.py
labs_cdk/labs_website_stack.py
labs_cdk/thoth_stack.py
labs_cdk/services/__init__.py
labs_cdk/services/ecr/__init__.py
labs_cdk/services/ecs/__init__.py
labs_cdk/services/ecs/alb_fargate_service.py
labs_cdk/services/ecs/container_repository.py
labs_cdk/services/ecs/standalone_ec2_service.py
labs_cdk/services/ecs/standalone_fargate_service.py
labs_cdk/services/elasticache/__init__.py
labs_cdk/services/elasticache/redis.py
labs_cdk/services/networking/__init__.py
labs_cdk/services/networking/vpc_private_isolated_subnets.py
labs_cdk/services/rds/__init__.py
labs_cdk/services/rds/postgres.py
labs_cdk/services/rds/secret.py
labs_cdk/services/storage/__init__.py
labs_cdk/services/storage/s3.py
services/__init__.py
services/ecs/__init__.py
services/ecs/alb_fargate_service.py
services/ecs/container_repository.py
services/ecs/standalone_fargate_service.py
services/elasticache/__init__.py
services/elasticache/redis.py
services/networking/__init__.py
services/networking/vpc_private_isolated_subnets.py
services/rds/__init__.py
services/rds/postgres.py
services/rds/secret.py
services/storage/__init__.py
services/storage/s3.py
labs_cdk-0.0.19.dist-info/METADATA
labs_cdk-0.0.19.dist-info/WHEEL
labs_cdk-0.0.19.dist-info/top_level.txt
labs_cdk-0.0.19.dist-info/RECORD
