Metadata-Version: 2.1
Name: labs-cdk
Version: 0.0.19
Summary: GIC Labs AWS CDK constructs
Home-page: https://github.com/GICLabs/labs-cdk
Author: Vaibhav Bansal
Author-email: vaibhavbansal@gic.com.sg
License: UNKNOWN
Platform: UNKNOWN
Classifier: Intended Audience :: Developers
Classifier: Programming Language :: Python :: 3 :: Only
Classifier: Programming Language :: Python :: 3.6
Classifier: Programming Language :: Python :: 3.7
Classifier: Programming Language :: Python :: 3.8
Requires-Python: >=3.6
Requires-Dist: attrs (==20.2.0)
Requires-Dist: aws-cdk.assets (==1.62.0)
Requires-Dist: aws-cdk.aws-apigateway (==1.62.0)
Requires-Dist: aws-cdk.aws-applicationautoscaling (==1.62.0)
Requires-Dist: aws-cdk.aws-autoscaling (==1.62.0)
Requires-Dist: aws-cdk.aws-autoscaling-common (==1.62.0)
Requires-Dist: aws-cdk.aws-autoscaling-hooktargets (==1.62.0)
Requires-Dist: aws-cdk.aws-batch (==1.62.0)
Requires-Dist: aws-cdk.aws-certificatemanager (==1.62.0)
Requires-Dist: aws-cdk.aws-cloudformation (==1.62.0)
Requires-Dist: aws-cdk.aws-cloudfront (==1.62.0)
Requires-Dist: aws-cdk.aws-cloudwatch (==1.62.0)
Requires-Dist: aws-cdk.aws-codebuild (==1.62.0)
Requires-Dist: aws-cdk.aws-codecommit (==1.62.0)
Requires-Dist: aws-cdk.aws-codeguruprofiler (==1.62.0)
Requires-Dist: aws-cdk.aws-codepipeline (==1.62.0)
Requires-Dist: aws-cdk.aws-cognito (==1.62.0)
Requires-Dist: aws-cdk.aws-ec2 (==1.62.0)
Requires-Dist: aws-cdk.aws-ecr (==1.62.0)
Requires-Dist: aws-cdk.aws-ecr-assets (==1.62.0)
Requires-Dist: aws-cdk.aws-ecs (==1.62.0)
Requires-Dist: aws-cdk.aws-ecs-patterns (==1.62.0)
Requires-Dist: aws-cdk.aws-efs (==1.62.0)
Requires-Dist: aws-cdk.aws-elasticache (==1.62.0)
Requires-Dist: aws-cdk.aws-elasticloadbalancing (==1.62.0)
Requires-Dist: aws-cdk.aws-elasticloadbalancingv2 (==1.62.0)
Requires-Dist: aws-cdk.aws-events (==1.62.0)
Requires-Dist: aws-cdk.aws-events-targets (==1.62.0)
Requires-Dist: aws-cdk.aws-iam (==1.62.0)
Requires-Dist: aws-cdk.aws-kinesis (==1.62.0)
Requires-Dist: aws-cdk.aws-kms (==1.62.0)
Requires-Dist: aws-cdk.aws-lambda (==1.62.0)
Requires-Dist: aws-cdk.aws-logs (==1.62.0)
Requires-Dist: aws-cdk.aws-rds (==1.62.0)
Requires-Dist: aws-cdk.aws-route53 (==1.62.0)
Requires-Dist: aws-cdk.aws-route53-targets (==1.62.0)
Requires-Dist: aws-cdk.aws-s3 (==1.62.0)
Requires-Dist: aws-cdk.aws-s3-assets (==1.62.0)
Requires-Dist: aws-cdk.aws-sam (==1.62.0)
Requires-Dist: aws-cdk.aws-secretsmanager (==1.62.0)
Requires-Dist: aws-cdk.aws-servicediscovery (==1.62.0)
Requires-Dist: aws-cdk.aws-sns (==1.62.0)
Requires-Dist: aws-cdk.aws-sns-subscriptions (==1.62.0)
Requires-Dist: aws-cdk.aws-sqs (==1.62.0)
Requires-Dist: aws-cdk.aws-ssm (==1.62.0)
Requires-Dist: aws-cdk.aws-stepfunctions (==1.62.0)
Requires-Dist: aws-cdk.cdk-assets-schema (==1.41.0)
Requires-Dist: aws-cdk.cloud-assembly-schema (==1.62.0)
Requires-Dist: aws-cdk.core (==1.62.0)
Requires-Dist: aws-cdk.custom-resources (==1.62.0)
Requires-Dist: aws-cdk.cx-api (==1.62.0)
Requires-Dist: aws-cdk.region-info (==1.62.0)
Requires-Dist: cattrs (==1.0.0)
Requires-Dist: constructs (==3.0.4)
Requires-Dist: jsii (==1.12.0)
Requires-Dist: publication (==0.0.3)
Requires-Dist: python-dateutil (==2.8.1)
Requires-Dist: six (==1.15.0)
Requires-Dist: typing-extensions (==3.7.4.2)
